LICENSE.md
MANIFEST.in
README.md
setup.cfg
setup.py
version.py
limix_plot/__init__.py
limix_plot/_consensus.py
limix_plot/_dataset.py
limix_plot/_image.py
limix_plot/_kinship.py
limix_plot/_manhattan.py
limix_plot/_misc.py
limix_plot/_normal.py
limix_plot/_pca.py
limix_plot/_plt.py
limix_plot/_power.py
limix_plot/_qqplot.py
limix_plot/_show.py
limix_plot/_testit.py
limix_plot/conftest.py
limix_plot.egg-info/PKG-INFO
limix_plot.egg-info/SOURCES.txt
limix_plot.egg-info/dependency_links.txt
limix_plot.egg-info/requires.txt
limix_plot.egg-info/top_level.txt
limix_plot.egg-info/zip-safe